mewing_dl/__init__.py
mewing_dl/tasks.py
mewing_dl-0.1.dist-info/METADATA
mewing_dl-0.1.dist-info/WHEEL
mewing_dl-0.1.dist-info/top_level.txt
mewing_dl-0.1.dist-info/RECORD
